sklearn_freezer/__init__.py
sklearn_freezer/backend/__init__.py
sklearn_freezer/backend/c_compiler.py
sklearn_freezer/backend/core.py
sklearn_freezer/backend/cython_compiler.py
sklearn_freezer/backend/python_compiler.py
sklearn_freezer/backend/utils.py
sklearn_freezer/codegen/__init__.py
sklearn_freezer/codegen/decision_tree_classifier.py
sklearn_freezer/codegen/forest_classifier.py
sklearn_freezer-0.2.0.dist-info/METADATA
sklearn_freezer-0.2.0.dist-info/WHEEL
sklearn_freezer-0.2.0.dist-info/licenses/LICENSE
sklearn_freezer-0.2.0.dist-info/RECORD
