Metadata-Version: 2.4
Name: sklearn_freezer
Version: 0.2.0
Summary: Utility package for compiling scikit-learn classifiers for faster single-sample inference
Project-URL: Homepage, https://github.com/xsjk/Sklearn-Freezer
Project-URL: Repository, https://github.com/xsjk/Sklearn-Freezer
Author-email: xsjk <xsjk17@outlook.com>
License-Expression: MIT
License-File: LICENSE
Classifier: Development Status :: 2 - Pre-Alpha
Classifier: Environment :: Console
Classifier: Intended Audience :: Developers
Classifier: Intended Audience :: Science/Research
Classifier: Natural Language :: English
Classifier: Operating System :: OS Independent
Classifier: Programming Language :: Python :: 3
Classifier: Programming Language :: Python :: 3.10
Classifier: Programming Language :: Python :: 3.11
Classifier: Programming Language :: Python :: 3.12
Classifier: Programming Language :: Python :: 3.13
Classifier: Topic :: Software Development :: Libraries :: Python Modules
Classifier: Topic :: Utilities
Classifier: Typing :: Typed
Requires-Python: >=3.10
Requires-Dist: scikit-learn
Provides-Extra: all
Requires-Dist: cython; extra == 'all'
Requires-Dist: setuptools; extra == 'all'
